README.md
setup.py
flush/__init__.py
flush/main.py
flush.egg-info/PKG-INFO
flush.egg-info/SOURCES.txt
flush.egg-info/dependency_links.txt
flush.egg-info/entry_points.txt
flush.egg-info/not-zip-safe
flush.egg-info/requires.txt
flush.egg-info/top_level.txt