Metadata-Version: 2.1
Name: flush
Version: 0.3
Summary: Archive PostgreSQL tables to S3
Home-page: http://github.com/bcollazo/flush
Author: Bryan Collazo
Author-email: bcollazo2010@gmail.com
License: MIT
Platform: UNKNOWN
Classifier: Development Status :: 5 - Production/Stable
Classifier: Environment :: Console
Classifier: License :: OSI Approved :: MIT License
Classifier: Operating System :: OS Independent
Classifier: Programming Language :: Python :: 3.7
